asr2clip/__init__.py
asr2clip/asr2clip.py
asr2clip-0.3.6.dist-info/LICENSE
asr2clip-0.3.6.dist-info/METADATA
asr2clip-0.3.6.dist-info/WHEEL
asr2clip-0.3.6.dist-info/entry_points.txt
asr2clip-0.3.6.dist-info/top_level.txt
asr2clip-0.3.6.dist-info/RECORD
