Metadata-Version: 2.1
Name: asr2clip
Version: 0.3.6
Summary: A real-time speech-to-text clipboard tool.
Home-page: https://github.com/Oaklight/asr2clip
Author: Oaklight
Author-email: oaklight@gmx.com
License: GNU Affero General Public License v3
Classifier: Programming Language :: Python :: 3
Classifier: License :: OSI Approved :: GNU Affero General Public License v3
Classifier: Operating System :: OS Independent
Requires-Python: >=3.8
License-File: LICENSE
Requires-Dist: numpy>=1.24.4
Requires-Dist: openai>=1.59.6
Requires-Dist: pyperclip>=1.9.0
Requires-Dist: PyYAML>=6.0.2
Requires-Dist: requests>=2.32.3
Requires-Dist: scipy>=1.10.1
Requires-Dist: sounddevice>=0.5.1
Requires-Dist: pydub>=0.25.1
Requires-Dist: ffmpeg>=1.4
